zohocrm_prefect_tasks/__init__.py
zohocrm_prefect_tasks/_version.py
zohocrm_prefect_tasks/client.py
zohocrm_prefect_tasks/utils.py
zohocrm_prefect_tasks/aws/__init__.py
zohocrm_prefect_tasks/aws/secretsmanager_client.py
zohocrm_prefect_tasks/store/__init__.py
zohocrm_prefect_tasks/store/aws_secrets_manager_store.py
zohocrm_prefect_tasks/tasks/__init__.py
zohocrm_prefect_tasks/tasks/notes.py
zohocrm_prefect_tasks/tasks/records.py
zohocrm_prefect_tasks-0.0.15.dist-info/LICENSE
zohocrm_prefect_tasks-0.0.15.dist-info/METADATA
zohocrm_prefect_tasks-0.0.15.dist-info/WHEEL
zohocrm_prefect_tasks-0.0.15.dist-info/top_level.txt
zohocrm_prefect_tasks-0.0.15.dist-info/RECORD
