Metadata-Version: 2.1
Name: zohocrm-prefect-tasks
Version: 0.0.15
Home-page: https://github.com/aporacloudmobile/zohocrm_prefect_tasks
Author: Carlos Paiva
Author-email: carlospaiva87@gmail.com
Classifier: Programming Language :: Python :: 3
Classifier: Operating System :: OS Independent
Requires-Python: >=3.6
License-File: LICENSE
Requires-Dist: requests >=2.25.1
Requires-Dist: jsonmerge >=1.8.0
Requires-Dist: versioneer ~=0.19
Requires-Dist: setuptools >=58.5.3
Requires-Dist: pytest >=6.1.0
Requires-Dist: prefect ==0.15.11
Requires-Dist: zcrmsdk ~=3.1.0
Requires-Dist: mysql-connector-python >=8.1.0
Requires-Dist: boto3 ~=1.28.50
Requires-Dist: botocore ~=1.31.50
